outbox_streaming/__init__.py
outbox_streaming/asyncio/__init__.py
outbox_streaming/asyncio/celery/__init__.py
outbox_streaming/asyncio/celery/publisher.py
outbox_streaming/asyncio/celery/sqlalchemy/__init__.py
outbox_streaming/asyncio/celery/sqlalchemy/outbox.py
outbox_streaming/asyncio/celery/sqlalchemy/storage.py
outbox_streaming/asyncio/celery/types.py
outbox_streaming/asyncio/common/__init__.py
outbox_streaming/asyncio/common/sqlalchemy/__init__.py
outbox_streaming/asyncio/common/sqlalchemy/storage.py
outbox_streaming/asyncio/kafka/__init__.py
outbox_streaming/asyncio/kafka/publisher.py
outbox_streaming/asyncio/kafka/sqlalchemy/__init__.py
outbox_streaming/asyncio/kafka/sqlalchemy/outbox.py
outbox_streaming/asyncio/kafka/sqlalchemy/storage.py
outbox_streaming/asyncio/kafka/types.py
outbox_streaming/celery/__init__.py
outbox_streaming/celery/outbox.py
outbox_streaming/celery/publisher.py
outbox_streaming/celery/sqlalchemy/__init__.py
outbox_streaming/celery/sqlalchemy/models.py
outbox_streaming/celery/sqlalchemy/storage.py
outbox_streaming/celery/types.py
outbox_streaming/common/__init__.py
outbox_streaming/common/sqlachemy/__init__.py
outbox_streaming/common/sqlachemy/base.py
outbox_streaming/common/sqlachemy/queries.py
outbox_streaming/common/sqlachemy/storage.py
outbox_streaming/common/types.py
outbox_streaming/kafka/__init__.py
outbox_streaming/kafka/publisher.py
outbox_streaming/kafka/sqlalchemy/__init__.py
outbox_streaming/kafka/sqlalchemy/models.py
outbox_streaming/kafka/sqlalchemy/outbox.py
outbox_streaming/kafka/sqlalchemy/storage.py
outbox_streaming/kafka/types.py
outbox_streaming-0.1.0.dist-info/WHEEL
outbox_streaming-0.1.0.dist-info/METADATA
outbox_streaming-0.1.0.dist-info/RECORD
