Metadata-Version: 2.1
Name: outbox-streaming
Version: 0.1.0
Summary: 
Author: Yevhenii Hyzyla
Author-email: hyzyla@gmail.com
Requires-Python: >=3.10,<4.0
Classifier: Programming Language :: Python :: 3
Classifier: Programming Language :: Python :: 3.10
Provides-Extra: test
Requires-Dist: SQLAlchemy[asyncio] (>=1.4,<2.0); extra == "test"
Requires-Dist: aiokafka (>=0.7.2,<0.8.0); extra == "test"
Requires-Dist: celery (>=5.2.7,<6.0.0); extra == "test"
Requires-Dist: kafka-python (>=2.0.2,<3.0.0); extra == "test"
Requires-Dist: psycopg2-binary (>=2.9.3,<3.0.0); extra == "test"
